tds_client/__init__.py
tds_client/client.py
tds_client/dataset.py
tds_client/settings.py
tds_client/version.py
tds_client/catalog/__init__.py
tds_client/catalog/catalog.py
tds_client/catalog/common.py
tds_client/catalog/search.py
tds_client/service/__init__.py
tds_client/service/httpserver.py
tds_client/service/manager.py
tds_client/service/ncss.py
tds_client/service/opendap.py
tds_client/service/service.py
tds_client/util/__init__.py
tds_client/util/strings.py
tds_client/util/urls.py
tds_client/util/xml.py
eratos_tds-1.3.0.dist-info/METADATA
eratos_tds-1.3.0.dist-info/WHEEL
eratos_tds-1.3.0.dist-info/licenses/LICENSE
eratos_tds-1.3.0.dist-info/RECORD
