Metadata-Version: 2.4
Name: eratos-tds
Version: 1.3.0
Summary: Thredds Data Server (TDS) Client
Project-URL: Homepage, https://bitbucket.csiro.au/projects/SC/repos/tds-client-python/browse
Author-email: Mac Coombe <mac.coombe@csiro.au>
Maintainer-email: Eratos <support@eratos.com>
License-File: LICENSE
Keywords: Thredds
Classifier: Development Status :: 3 - Alpha
Classifier: Intended Audience :: Developers
Classifier: Natural Language :: English
Classifier: Operating System :: POSIX
Classifier: Programming Language :: Python :: 3.7
Classifier: Programming Language :: Python :: 3.8
Classifier: Programming Language :: Python :: 3.9
Classifier: Programming Language :: Python :: 3.10
Classifier: Programming Language :: Python :: 3.11
Classifier: Programming Language :: Python :: 3.12
Classifier: Topic :: Scientific/Engineering :: Information Analysis
Requires-Python: >=3
Requires-Dist: netcdf4
Requires-Dist: pydap
Requires-Dist: pydap[server]
Requires-Dist: requests
